[
  {
    "column_name": "id",
    "data_type": "integer",
    "is_nullable": "NO"
  },
  {
    "column_name": "producto_id",
    "data_type": "integer",
    "is_nullable": "YES"
  },
  {
    "column_name": "bodega_origen",
    "data_type": "integer",
    "is_nullable": "YES"
  },
  {
    "column_name": "bodega_destino",
    "data_type": "integer",
    "is_nullable": "YES"
  },
  {
    "column_name": "tipo",
    "data_type": "character varying",
    "is_nullable": "NO"
  },
  {
    "column_name": "cantidad",
    "data_type": "integer",
    "is_nullable": "NO"
  },
  {
    "column_name": "usuario_id",
    "data_type": "integer",
    "is_nullable": "YES"
  },
  {
    "column_name": "fecha",
    "data_type": "timestamp without time zone",
    "is_nullable": "NO"
  },
  {
    "column_name": "motivo",
    "data_type": "text",
    "is_nullable": "YES"
  },
  {
    "column_name": "documento_asociado",
    "data_type": "character varying",
    "is_nullable": "YES"
  }
]